pyhyypapihawkmod/__init__.py
pyhyypapihawkmod/__main__.py
pyhyypapihawkmod/alarm_info.py
pyhyypapihawkmod/client.py
pyhyypapihawkmod/common_tools.py
pyhyypapihawkmod/constants.py
pyhyypapihawkmod/exceptions.py
pyhyypapihawkmod/imei.py
pyhyypapihawkmod-1.5.2.dist-info/licenses/LICENSE.md
pyhyypapihawkmod-1.5.2.dist-info/METADATA
pyhyypapihawkmod-1.5.2.dist-info/WHEEL
pyhyypapihawkmod-1.5.2.dist-info/top_level.txt
pyhyypapihawkmod-1.5.2.dist-info/RECORD
